dcollector/__init__.py
dcollector/main.py
dcollector/providers/__init__.py
dcollector/providers/aws.py
dcollector/providers/cloudflare.py
dcollector/providers/cycognito.py
dcollector/providers/digitalocean.py
dcollector/providers/file.py
dcollector/providers/gcp.py
dcollector/providers/ns1.py
dcollector/providers/prisma.py
dcollector/utils/__init__.py
dcollector/utils/utils.py
D_Collector-0.10.dist-info/LICENSE
D_Collector-0.10.dist-info/METADATA
D_Collector-0.10.dist-info/WHEEL
D_Collector-0.10.dist-info/entry_points.txt
D_Collector-0.10.dist-info/top_level.txt
D_Collector-0.10.dist-info/RECORD
