Metadata-Version: 2.1
Name: D-Collector
Version: 0.10
Summary: Collect DNS records from various DNS and cloud providers.
Home-page: https://github.com/Playtika/d-collector
Author: Playtika Ltd.
Author-email: security@playtika.com
Classifier: Programming Language :: Python :: 3
Classifier: License :: OSI Approved :: Apache Software License
Classifier: Operating System :: OS Independent
Requires-Python: >=3.7
License-File: LICENSE
Requires-Dist: requests==2.32.3
Requires-Dist: boto3==1.35.59
Requires-Dist: google_api_python_client==2.44.0
Requires-Dist: protobuf==4.21.6
Requires-Dist: python_digitalocean==1.17.0
Requires-Dist: urllib3==1.26.20
Requires-Dist: certifi==2024.7.4
Requires-Dist: zipp==3.21.0
